tests/__init__.py
tests/test_pairing.py
tingpy/__init__.py
tingpy/client.py
tingpy/pairing.py
tingpy-0.1.0.dist-info/licenses/LICENSE.txt
tingpy-0.1.0.dist-info/METADATA
tingpy-0.1.0.dist-info/WHEEL
tingpy-0.1.0.dist-info/top_level.txt
tingpy-0.1.0.dist-info/RECORD
