Metadata-Version: 2.4
Name: tingpy
Version: 0.1.0
Summary: A developer-friendly wrapper for Firebase Cloud Messaging with QR code pairing
Home-page: https://github.com/shithaarthan/tingpy
Author: TingPy Team
Author-email: team@tingpy.com
License: MIT
Classifier: Programming Language :: Python :: 3
Classifier: Operating System :: OS Independent
Requires-Python: >=3.6
License-File: LICENSE.txt
Requires-Dist: firebase-admin
Requires-Dist: segno
Dynamic: author
Dynamic: author-email
Dynamic: classifier
Dynamic: description
Dynamic: description-content-type
Dynamic: home-page
Dynamic: license
Dynamic: license-file
Dynamic: requires-dist
Dynamic: requires-python
Dynamic: summary
